wpd/VERSION
wpd/__main__.py
WPD-0.1.1.dist-info/LICENSE
WPD-0.1.1.dist-info/METADATA
WPD-0.1.1.dist-info/WHEEL
WPD-0.1.1.dist-info/entry_points.txt
WPD-0.1.1.dist-info/top_level.txt
WPD-0.1.1.dist-info/RECORD
