Metadata-Version: 2.1
Name: WPD
Version: 0.1.1
Summary: Render html to pdf with weasyprint, controled from stdin
Home-page: https://orus.io/orus-io/wpd
Author: Orus Dev Team
Author-email: contact@orus.io
License: UNKNOWN
Platform: UNKNOWN
Requires-Dist: weasyprint (>=51)
